cruiser/__init__.py
cruiser/caculator.py
cruiser/config_parse.py
cruiser/main.py
cruiser-0.0.1.dist-info/DESCRIPTION.rst
cruiser-0.0.1.dist-info/METADATA
cruiser-0.0.1.dist-info/RECORD
cruiser-0.0.1.dist-info/WHEEL
cruiser-0.0.1.dist-info/entry_points.txt
cruiser-0.0.1.dist-info/metadata.json
cruiser-0.0.1.dist-info/top_level.txt
